AUTHORS
LICENSE
MANIFEST.in
README.txt
setup.py
django_mongo_storage.egg-info/PKG-INFO
django_mongo_storage.egg-info/SOURCES.txt
django_mongo_storage.egg-info/dependency_links.txt
django_mongo_storage.egg-info/not-zip-safe
django_mongo_storage.egg-info/requires.txt
django_mongo_storage.egg-info/top_level.txt
mongo_storage/__init__.py
mongo_storage/admin.py
mongo_storage/fields.py
mongo_storage/models.py
mongo_storage/storage.py
mongo_storage/tests.py
mongo_storage/views.py