Metadata-Version: 1.0
Name: django-mongo-storage
Version: 0.3.1
Summary: A mongo GridFS storage backend for django.
Home-page: https://github.com/madisona/django-mongo-storage
Author: Aaron Madison
Author-email: aaron.l.madison@gmail.com
License: UNKNOWN
Platform: UNKNOWN
Classifier: Development Status :: 3 - Alpha
Classifier: Environment :: Web Environment
Classifier: Framework :: Django
Classifier: Intended Audience :: Developers
Classifier: License :: OSI Approved :: BSD License
Classifier: Operating System :: OS Independent
Classifier: Programming Language :: Python
Classifier: Topic :: Software Development
Classifier: Topic :: Software Development :: Libraries :: Application Frameworks
